intersim/__init__.py
intersim/box.py
intersim/collisions.py
intersim/datautils.py
intersim/graph.py
intersim/policy.py
intersim/simulator.py
intersim/vehicletraj.py
intersim/default_graphs/__init__.py
intersim/default_graphs/closestobstacle.py
intersim/default_graphs/conevisibility.py
intersim/viz/__init__.py
intersim/viz/animatedviz.py
intersim/viz/dict_utils.py
intersim/viz/utils.py
InteractionSimulator-0.0.2.dist-info/LICENSE
InteractionSimulator-0.0.2.dist-info/METADATA
InteractionSimulator-0.0.2.dist-info/WHEEL
InteractionSimulator-0.0.2.dist-info/top_level.txt
InteractionSimulator-0.0.2.dist-info/zip-safe
InteractionSimulator-0.0.2.dist-info/RECORD
