Metadata-Version: 2.1
Name: InteractionSimulator
Version: 0.0.2
Summary: Simulator environment for INTERACTION driving dataset
Home-page: https://github.com/sisl/InteractionSimulator
Author: Kunal Menda, Arec Jamgochian
Author-email: jamgochian95@gmail.com
License: MIT
Platform: UNKNOWN
Classifier: Programming Language :: Python :: 3
Classifier: License :: OSI Approved :: MIT License
Classifier: Operating System :: OS Independent
Classifier: Development Status :: 4 - Beta
Requires-Python: >=3.6
License-File: LICENSE
Requires-Dist: click
Requires-Dist: joblib
Requires-Dist: pandas
Requires-Dist: matplotlib
Requires-Dist: numpy
Requires-Dist: scipy
Requires-Dist: torch
Requires-Dist: termcolor
Requires-Dist: python-dateutil
Requires-Dist: gym
Requires-Dist: future
Requires-Dist: sklearn
Requires-Dist: pyproj
Requires-Dist: pytest
